README.rst
hibget
setup.cfg
setup.py
bin/hibget
hibget/__init__.py
hibget/requests_logging.py
hibget/utils.py
hibget/widgets.py
hibget.egg-info/PKG-INFO
hibget.egg-info/SOURCES.txt
hibget.egg-info/dependency_links.txt
hibget.egg-info/requires.txt
hibget.egg-info/top_level.txt