Metadata-Version: 1.1
Name: hibget
Version: 0.0.2
Summary: Humble Indie Bundle Downloader
Home-page: https://github.com/saik0/hibget
Author: Joel Pedraza
Author-email: joel@joelpedraza.com
License: UNKNOWN
Download-URL: https://github.com/saik0/hibget/tarball/0.0.2
Platform: UNKNOWN
